commodore/__init__.py
commodore/__main__.py
commodore/catalog.py
commodore/cli/__init__.py
commodore/cli/catalog.py
commodore/cli/component.py
commodore/cli/inventory.py
commodore/cli/oidc.py
commodore/cli/options.py
commodore/cli/package.py
commodore/cli/tool.py
commodore/cluster.py
commodore/compile.py
commodore/component/__init__.py
commodore/component/compile.py
commodore/component/template.py
commodore/config.py
commodore/dependency_mgmt/__init__.py
commodore/dependency_mgmt/component_library.py
commodore/dependency_mgmt/discovery.py
commodore/dependency_mgmt/jsonnet_bundler.py
commodore/dependency_mgmt/tools.py
commodore/dependency_mgmt/version_parsing.py
commodore/dependency_syncer.py
commodore/dependency_templater.py
commodore/filters/helm_namespace.jsonnet
commodore/gitrepo/__init__.py
commodore/gitrepo/diff.py
commodore/helpers.py
commodore/inventory/__init__.py
commodore/inventory/lint.py
commodore/inventory/lint_dependency_specification.py
commodore/inventory/lint_deprecated_parameters.py
commodore/inventory/parameters.py
commodore/inventory/render.py
commodore/k8sobject.py
commodore/lib/commodore.libjsonnet
commodore/lib/kube-libsonnet/kube.libsonnet
commodore/lib/kube.libjsonnet
commodore/lib/kube.libsonnet
commodore/login.py
commodore/multi_dependency.py
commodore/normalize_url.py
commodore/package/__init__.py
commodore/package/compile.py
commodore/package/template.py
commodore/postprocess/__init__.py
commodore/postprocess/builtin_filters.py
commodore/postprocess/jsonnet.py
commodore/refs.py
commodore/scripts/run-kustomize
commodore/tokencache.py
commodore/tools.py
commodore/version.py
syn_commodore-1.31.0.dist-info/METADATA
syn_commodore-1.31.0.dist-info/WHEEL
syn_commodore-1.31.0.dist-info/entry_points.txt
syn_commodore-1.31.0.dist-info/licenses/LICENSE
syn_commodore-1.31.0.dist-info/RECORD
