Metadata-Version: 2.4
Name: syn-commodore
Version: 1.31.0
Summary: Commodore provides opinionated tenant-aware management of Kapitan inventories and templates. Commodore uses Kapitan for the heavy lifting of rendering templates and resolving a hierachical configuration structure.
License: BSD-3-Clause
License-File: LICENSE
Author: VSHN AG
Author-email: info@vshn.ch
Requires-Python: >=3.10,<3.13
Classifier: License :: OSI Approved :: BSD License
Classifier: Programming Language :: Python :: 3
Classifier: Programming Language :: Python :: 3.10
Classifier: Programming Language :: Python :: 3.11
Classifier: Programming Language :: Python :: 3.12
Requires-Dist: PyGithub (==2.8.1)
Requires-Dist: boto3 (>=1.26.145,<2.0.0)
Requires-Dist: botocore (>=1.29.145,<2.0.0)
Requires-Dist: click (==8.3.1)
Requires-Dist: cruft (==2.16.0)
Requires-Dist: gitpython (==3.1.46)
Requires-Dist: gojsonnet (==0.21.0)
Requires-Dist: kapitan (==0.34.7)
Requires-Dist: oauthlib (==3.3.1)
Requires-Dist: pygobuildinfo (==0.1.27)
Requires-Dist: pyjwt (==2.10.1)
Requires-Dist: python-dotenv (==1.2.1)
Requires-Dist: pyxdg (==0.28)
Requires-Dist: reclass-rs (==0.10.1)
Requires-Dist: requests (==2.32.5)
Requires-Dist: url-normalize (==2.2.1)
Project-URL: Documentation, https://syn.tools/commodore/index.html
Project-URL: Homepage, https://github.com/projectsyn/commodore
